{
    "fluentMethods": true,
    "clientRootFolder": "",
    "relationships": [
        {
            "relationshipType": "many-to-one",
            "otherEntityName": "cliente",
            "otherEntityRelationshipName": "venta",
            "relationshipName": "cliente",
            "otherEntityField": "id"
        },
        {
            "relationshipType": "many-to-many",
            "otherEntityName": "producto",
            "otherEntityRelationshipName": "venta",
            "relationshipName": "producto",
            "otherEntityField": "id",
            "ownerSide": true
        },
        {
            "relationshipType": "many-to-many",
            "otherEntityName": "videoJuegos",
            "otherEntityRelationshipName": "venta",
            "relationshipName": "videoJuegos",
            "otherEntityField": "id",
            "ownerSide": true
        }
    ],
    "fields": [
        {
            "fieldName": "fechaVenta",
            "fieldType": "LocalDate"
        },
        {
            "fieldName": "precioVenta",
            "fieldType": "Double"
        }
    ],
    "changelogDate": "20221205085426",
    "dto": "mapstruct",
    "searchEngine": false,
    "service": "serviceImpl",
    "entityTableName": "venta",
    "databaseType": "sql",
    "jpaMetamodelFiltering": false,
    "pagination": "pagination"
}
